CollabConnector/__init__.py
CollabConnector/CER/CER.py
CollabConnector/CER/__init__.py
CollabConnector/CUCM/CUCM.py
CollabConnector/CUCM/Regex.py
CollabConnector/CUCM/__init__.py
CollabConnector/CUCM/AST/AST.py
CollabConnector/CUCM/AST/__init__.py
CollabConnector/CUCM/AXL/AXL.py
CollabConnector/CUCM/AXL/__init__.py
CollabConnector/CUCM/AXL/schema/10.0/AXLAPI.wsdl
CollabConnector/CUCM/AXL/schema/10.0/AXLEnums.xsd
CollabConnector/CUCM/AXL/schema/10.0/AXLSoap.xsd
CollabConnector/CUCM/AXL/schema/10.5/AXLAPI.wsdl
CollabConnector/CUCM/AXL/schema/10.5/AXLEnums.xsd
CollabConnector/CUCM/AXL/schema/10.5/AXLSoap.xsd
CollabConnector/CUCM/AXL/schema/11.0/AXLAPI.wsdl
CollabConnector/CUCM/AXL/schema/11.0/AXLEnums.xsd
CollabConnector/CUCM/AXL/schema/11.0/AXLSoap.xsd
CollabConnector/CUCM/AXL/schema/11.5/AXLAPI.wsdl
CollabConnector/CUCM/AXL/schema/11.5/AXLEnums.xsd
CollabConnector/CUCM/AXL/schema/11.5/AXLSoap.xsd
CollabConnector/CUCM/AXL/schema/12.0/AXLAPI.wsdl
CollabConnector/CUCM/AXL/schema/12.0/AXLEnums.xsd
CollabConnector/CUCM/AXL/schema/12.0/AXLSoap.xsd
CollabConnector/CUCM/AXL/schema/12.5/AXLAPI.wsdl
CollabConnector/CUCM/AXL/schema/12.5/AXLEnums.xsd
CollabConnector/CUCM/AXL/schema/12.5/AXLSoap.xsd
CollabConnector/CUCM/AXL/schema/12.5/ControlCenterServices.wsdl
CollabConnector/CUCM/AXL/schema/12.5/PerfmonService.wsdl
CollabConnector/CUCM/AXL/schema/12.5/RISService70.wsdl
CollabConnector/CUCM/AXL/schema/14.0/AXLAPI.wsdl
CollabConnector/CUCM/AXL/schema/14.0/AXLEnums.xsd
CollabConnector/CUCM/AXL/schema/14.0/AXLSoap.xsd
CollabConnector/CUCM/AXL/schema/15.0/AXLAPI.wsdl
CollabConnector/CUCM/AXL/schema/15.0/AXLEnums.xsd
CollabConnector/CUCM/AXL/schema/15.0/AXLSoap.xsd
CollabConnector/CUCM/AXL/schema/7.1/AXLAPI.wsdl
CollabConnector/CUCM/AXL/schema/7.1/AXLEnums.xsd
CollabConnector/CUCM/AXL/schema/7.1/axl.xsd
CollabConnector/CUCM/AXL/schema/7.1/axlmessage.xsd
CollabConnector/CUCM/AXL/schema/8.0/AXLAPI.wsdl
CollabConnector/CUCM/AXL/schema/8.0/AXLEnums.xsd
collabconnector-0.1.1754924847.dist-info/METADATA
collabconnector-0.1.1754924847.dist-info/WHEEL
collabconnector-0.1.1754924847.dist-info/licenses/LICENSE
collabconnector-0.1.1754924847.dist-info/RECORD
