Metadata-Version: 2.4
Name: CollabConnector
Version: 0.1.1754924847
Summary: An attempt at a simplified API collection for Cisco Collab products
Project-URL: Homepage, https://github.com/mycollablab/CollabConnector
Project-URL: Repository, https://github.com/mycollablab/CollabConnector
Project-URL: Bug Tracker, https://github.com/mycollablab/CollabConnector/issues
Author-email: Jon Snipes <jsnipes@mycollablab.org>
License-Expression: MIT
License-File: LICENSE
Keywords: api,cisco,collaboration,cucm,webex
Classifier: Development Status :: 4 - Beta
Classifier: Intended Audience :: Developers
Classifier: Operating System :: OS Independent
Classifier: Programming Language :: Python :: 3
Classifier: Programming Language :: Python :: 3.8
Classifier: Programming Language :: Python :: 3.9
Classifier: Programming Language :: Python :: 3.10
Classifier: Programming Language :: Python :: 3.11
Classifier: Programming Language :: Python :: 3.12
Classifier: Topic :: Communications
Classifier: Topic :: Software Development :: Libraries :: Python Modules
Requires-Python: >=3.8
Requires-Dist: openpyxl>=3.1.2
Requires-Dist: pandas>=1.5.3
Requires-Dist: requests>=2.28.1
Requires-Dist: xmltodict>=0.13.0
Requires-Dist: zeep>=4.1.0
